{"id":"1400aa77-4df5-447c-be66-96e2208c4e5b","slug":"ivyjournal","values":{"Description":"Use this simple python program to make a file based encrypted text storage system. It uses the python cryptography module.","End Date":"August 2021","Images":["827d1f54-9839-433d-90f6-cf901624f6f2.png"],"Other URLs":"","Repo URL":"https://github.com/vachanmn123/IvyJournal","Start Date":"August 2021","Tagline":"A simple encrypted journal","Technologies":"Python, Cryptography","Title":"IvyJournal","Video URL":"youtube.com/watch?v=IhLFavjRGTk\u0026feature=youtu.be"}}